numerai/__init__.py
numerai/cli/__init__.py
numerai/cli/constants.py
numerai/cli/destroy_all.py
numerai/cli/doctor.py
numerai/cli/misc.py
numerai/cli/setup.py
numerai/cli/uninstall.py
numerai/cli/upgrade.py
numerai/cli/node/__init__.py
numerai/cli/node/config.py
numerai/cli/node/deploy.py
numerai/cli/node/destroy.py
numerai/cli/node/test.py
numerai/cli/util/__init__.py
numerai/cli/util/debug.py
numerai/cli/util/docker.py
numerai/cli/util/files.py
numerai/cli/util/keys.py
numerai/cli/util/terraform.py
numerai/examples/crypto-python3/Dockerfile
numerai/examples/crypto-python3/predict.py
numerai/examples/crypto-python3/requirements.txt
numerai/examples/signals-python3/Dockerfile
numerai/examples/signals-python3/predict.py
numerai/examples/signals-python3/requirements.txt
numerai/examples/signals-python3/train.py
numerai/examples/tournament-python3/Dockerfile
numerai/examples/tournament-python3/predict.py
numerai/examples/tournament-python3/requirements.txt
numerai/examples/tournament-python3/train.py
numerai/examples/tournament-rlang/Dockerfile
numerai/examples/tournament-rlang/install_packages.R
numerai/examples/tournament-rlang/main.R
numerai/terraform/aws/-inputs.tf
numerai/terraform/aws/-main.tf
numerai/terraform/aws/-outputs.tf
numerai/terraform/aws/aws/-inputs.tf
numerai/terraform/aws/aws/-locals.tf
numerai/terraform/aws/aws/-outputs.tf
numerai/terraform/aws/aws/cluster.tf
numerai/terraform/aws/aws/main.zip
numerai/terraform/aws/aws/network.tf
numerai/terraform/aws/aws/webhook.tf
numerai/terraform/azure/azure_cron_trigger.zip
numerai/terraform/azure/azure_trigger.zip
numerai/terraform/azure/input.tf
numerai/terraform/azure/main.tf
numerai/terraform/azure/outputs.tf
numerai/terraform/azure/registry.tf
numerai/terraform/azure/azure/cluster.tf
numerai/terraform/azure/azure/input.tf
numerai/terraform/azure/azure/locals.tf
numerai/terraform/azure/azure/outputs.tf
numerai/terraform/azure/azure/webhook.tf
numerai/terraform/gcp/-inputs.tf
numerai/terraform/gcp/-main.tf
numerai_cli-1.1.3.dist-info/LICENSE
numerai_cli-1.1.3.dist-info/METADATA
numerai_cli-1.1.3.dist-info/WHEEL
numerai_cli-1.1.3.dist-info/entry_points.txt
numerai_cli-1.1.3.dist-info/top_level.txt
numerai_cli-1.1.3.dist-info/RECORD
