Metadata-Version: 2.1
Name: numerai-cli
Version: 1.1.3
Summary: A library for deploying Numer.ai Prediction Nodes.
Home-page: https://github.com/numerai/numerai-cli
Author: Numer.ai
Author-email: contact@numer.ai
License: MIT
Platform: UNKNOWN
Requires-Python: >=3.6.0
Requires-Dist: click >=7
Requires-Dist: boto3
Requires-Dist: botocore
Requires-Dist: numerapi >=2.4.5
Requires-Dist: colorama
Requires-Dist: requests
Requires-Dist: azure-identity
Requires-Dist: azure-mgmt-subscription
Requires-Dist: azure-mgmt-containerregistry
Requires-Dist: azure-containerregistry
Requires-Dist: azure-data-tables
Requires-Dist: azure-mgmt-storage
Requires-Dist: google-cloud-storage
Requires-Dist: google-cloud-run
Requires-Dist: google-cloud-artifact-registry
Requires-Dist: google-cloud-logging
